[
  {
    "INVOICE_NO": "THG231001643",
    "PO_NO": "1250505001",
    "ITEM_NO": "100169311",
    "QTY": "3600",
    "UNIT_PRICE": "10.5566",
    "AMOUNT": "38003.76"
  },
  {
    "INVOICE_NO": "THG231001643",
    "PO_NO": "1249224001",
    "ITEM_NO": "122786321",
    "QTY": "2100",
    "UNIT_PRICE": "20.1724",
    "AMOUNT": "42362.04"
  },
  {
    "INVOICE_NO": "THG231001643",
    "PO_NO": "1249224002",
    "ITEM_NO": "122786341",
    "QTY": "2100",
    "UNIT_PRICE": "19.0171",
    "AMOUNT": "39935.91"
  },
  {
    "INVOICE_NO": "THG231001643",
    "PO_NO": "1249779002",
    "ITEM_NO": "122786341",
    "QTY": "6300",
    "UNIT_PRICE": "19.0171",
    "AMOUNT": "119807.73"
  },
  {
    "INVOICE_NO": "THG231001643",
    "PO_NO": "9093432043",
    "ITEM_NO": "148711811",
    "QTY": "60000",
    "UNIT_PRICE": "4.7041",
    "AMOUNT": "282246.00"
  },
  {
    "INVOICE_NO": "THG231001643",
    "PO_NO": "1248847003",
    "ITEM_NO": "149323211",
    "QTY": "11400",
    "UNIT_PRICE": "27.6022",
    "AMOUNT": "314665.08"
  },
  {
    "INVOICE_NO": "THG231001643",
    "PO_NO": "1250505003",
    "ITEM_NO": "149323211",
    "QTY": "8550",
    "UNIT_PRICE": "27.6022",
    "AMOUNT": "235998.81"
  },
  {
    "INVOICE_NO": "THG231001643",
    "PO_NO": "1250099003",
    "ITEM_NO": "169260551",
    "QTY": "9000",
    "UNIT_PRICE": "1.9370",
    "AMOUNT": "17433.00"
  },
  {
    "INVOICE_NO": "THG231001643",
    "PO_NO": "1250099004",
    "ITEM_NO": "169260551",
    "QTY": "13500",
    "UNIT_PRICE": "1.9370",
    "AMOUNT": "26149.50"
  },
  {
    "INVOICE_NO": "THG231001643",
    "PO_NO": "1254543006",
    "ITEM_NO": "177124621",
    "QTY": "1800",
    "UNIT_PRICE": "3.9086",
    "AMOUNT": "7035.48"
  },
  {
    "INVOICE_NO": "THG231001643",
    "PO_NO": "1256350005",
    "ITEM_NO": "177124621",
    "QTY": "30600",
    "UNIT_PRICE": "3.9086",
    "AMOUNT": "119603.16"
  },
  {
    "INVOICE_NO": "THG231001643",
    "PO_NO": "1250099006",
    "ITEM_NO": "177144921",
    "QTY": "4500",
    "UNIT_PRICE": "1.2487",
    "AMOUNT": "5619.15"
  },
  {
    "INVOICE_NO": "THG231001643",
    "PO_NO": "1250505005",
    "ITEM_NO": "177173121",
    "QTY": "4500",
    "UNIT_PRICE": "3.3967",
    "AMOUNT": "15285.15"
  },
  {
    "INVOICE_NO": "THG231001643",
    "PO_NO": "1248847005",
    "ITEM_NO": "178668021",
    "QTY": "30000",
    "UNIT_PRICE": "3.3448",
    "AMOUNT": "100344.00"
  },
  {
    "INVOICE_NO": "THG231001643",
    "PO_NO": "1252820008",
    "ITEM_NO": "178691441",
    "QTY": "20000",
    "UNIT_PRICE": "0.5085",
    "AMOUNT": "10170.00"
  },
  {
    "INVOICE_NO": "THG231001643",
    "PO_NO": "1253406008",
    "ITEM_NO": "178691441",
    "QTY": "70000",
    "UNIT_PRICE": "0.5085",
    "AMOUNT": "35595.00"
  },
  {
    "INVOICE_NO": "THG231001643",
    "PO_NO": "1248974001",
    "ITEM_NO": "178691451",
    "QTY": "20000",
    "UNIT_PRICE": "0.5811",
    "AMOUNT": "11622.00"
  },
  {
    "INVOICE_NO": "THG231001643",
    "PO_NO": "1248847007",
    "ITEM_NO": "178691511",
    "QTY": "5000",
    "UNIT_PRICE": "3.4312",
    "AMOUNT": "17156.00"
  },
  {
    "INVOICE_NO": "THG231001643",
    "PO_NO": "1249422010",
    "ITEM_NO": "179813631",
    "QTY": "10000",
    "UNIT_PRICE": "2.1791",
    "AMOUNT": "21791.00"
  },
  {
    "INVOICE_NO": "THG231001643",
    "PO_NO": "1249422011",
    "ITEM_NO": "179813631",
    "QTY": "20000",
    "UNIT_PRICE": "2.1791",
    "AMOUNT": "43582.00"
  },
  {
    "INVOICE_NO": "THG231001643",
    "PO_NO": "1248847008",
    "ITEM_NO": "179842011",
    "QTY": "4000",
    "UNIT_PRICE": "3.2237",
    "AMOUNT": "12894.80"
  },
  {
    "INVOICE_NO": "THG231001643",
    "PO_NO": "1249422012",
    "ITEM_NO": "179842011",
    "QTY": "8000",
    "UNIT_PRICE": "3.2237",
    "AMOUNT": "25789.60"
  },
  {
    "INVOICE_NO": "THG231001643",
    "PO_NO": "1248974002",
    "ITEM_NO": "179842011",
    "QTY": "8000",
    "UNIT_PRICE": "3.2237",
    "AMOUNT": "25789.60"
  }
]